{
    "key": "group_599edf795c692",
    "title": "Yleiset sisällöt",
    "fields": [
        {
            "key": "field_59d7403d5bf31",
            "label": "Footer",
            "name": "",
            "type": "tab",
            "instructions": "",
            "required": 0,
            "conditional_logic": 0,
            "wrapper": {
                "width": "",
                "class": "",
                "id": ""
            },
            "placement": "left",
            "endpoint": 0
        },
        {
            "key": "field_5ee35532bf7e3",
            "label": "Footer yhteystiedot",
            "name": "footer_contact",
            "type": "wysiwyg",
            "instructions": "",
            "required": 0,
            "conditional_logic": 0,
            "wrapper": {
                "width": "",
                "class": "",
                "id": ""
            },
            "default_value": "",
            "tabs": "all",
            "toolbar": "basic",
            "media_upload": 0,
            "delay": 0
        },
        {
            "key": "field_5ee354937399e",
            "label": "Evästeet ja tietosuoja",
            "name": "",
            "type": "tab",
            "instructions": "",
            "required": 0,
            "conditional_logic": 0,
            "wrapper": {
                "width": "",
                "class": "",
                "id": ""
            },
            "placement": "left",
            "endpoint": 0
        },
        {
            "key": "field_5ee354a37399f",
            "label": "Näytä evästeilmoitus",
            "name": "cookies_show_notification",
            "type": "radio",
            "instructions": "",
            "required": 1,
            "conditional_logic": 0,
            "wrapper": {
                "width": "",
                "class": "",
                "id": ""
            },
            "choices": {
                "1": "Kyllä",
                "0": "Ei"
            },
            "allow_null": 0,
            "other_choice": 0,
            "default_value": "",
            "layout": "horizontal",
            "return_format": "value",
            "save_other_choice": 0
        },
        {
            "key": "field_5ee354c1739a0",
            "label": "Evästeilmoitus",
            "name": "cookies_notification",
            "type": "wysiwyg",
            "instructions": "",
            "required": 1,
            "conditional_logic": [
                [
                    {
                        "field": "field_5ee354a37399f",
                        "operator": "==",
                        "value": "1"
                    }
                ]
            ],
            "wrapper": {
                "width": "",
                "class": "",
                "id": ""
            },
            "default_value": "Käytämme sivustolla evästeitä käyttäjäkokemuksen parantamiseksi. Käyttämällä palvelua hyväksyt evästeiden käytön. <a href=\"#\">Lue lisää<\/a>.",
            "tabs": "all",
            "toolbar": "basic",
            "media_upload": 0,
            "delay": 0
        },
        {
            "key": "field_5ee354e1739a1",
            "label": "Hyväksymispainikkeen teksti",
            "name": "cookies_accept_text",
            "type": "text",
            "instructions": "",
            "required": 1,
            "conditional_logic": [
                [
                    {
                        "field": "field_5ee354a37399f",
                        "operator": "==",
                        "value": "1"
                    }
                ]
            ],
            "wrapper": {
                "width": "",
                "class": "",
                "id": ""
            },
            "default_value": "Ok",
            "placeholder": "",
            "prepend": "",
            "append": "",
            "maxlength": ""
        },
        {
            "key": "field_5f34e1a3cf6f4",
            "label": "Sosiaalinen media",
            "name": "",
            "type": "tab",
            "instructions": "",
            "required": 0,
            "conditional_logic": 0,
            "wrapper": {
                "width": "",
                "class": "",
                "id": ""
            },
            "placement": "left",
            "endpoint": 0
        },
        {
            "key": "field_5f34e22dcf6f9",
            "label": "Ohje",
            "name": "",
            "type": "message",
            "instructions": "",
            "required": 0,
            "conditional_logic": 0,
            "wrapper": {
                "width": "",
                "class": "",
                "id": ""
            },
            "message": "Nämä eivät ole jakopainikkeita vaan linkkejä sosiaalisenmedian sivuihin.",
            "new_lines": "wpautop",
            "esc_html": 0
        },
        {
            "key": "field_5f34e2db51fe7",
            "label": "Sosiaalinen media",
            "name": "social_media",
            "type": "group",
            "instructions": "",
            "required": 0,
            "conditional_logic": 0,
            "wrapper": {
                "width": "",
                "class": "",
                "id": ""
            },
            "layout": "block",
            "sub_fields": [
                {
                    "key": "field_5f34e1f9cf6f6",
                    "label": "Instagram",
                    "name": "instagram",
                    "type": "url",
                    "instructions": "",
                    "required": 0,
                    "conditional_logic": 0,
                    "wrapper": {
                        "width": "",
                        "class": "",
                        "id": ""
                    },
                    "default_value": "",
                    "placeholder": ""
                },
                {
                    "key": "field_5f34e20acf6f7",
                    "label": "Twitter",
                    "name": "twitter",
                    "type": "url",
                    "instructions": "",
                    "required": 0,
                    "conditional_logic": 0,
                    "wrapper": {
                        "width": "",
                        "class": "",
                        "id": ""
                    },
                    "default_value": "",
                    "placeholder": ""
                },
                {
                    "key": "field_5f34e215cf6f8",
                    "label": "Facebook",
                    "name": "facebook",
                    "type": "url",
                    "instructions": "",
                    "required": 0,
                    "conditional_logic": 0,
                    "wrapper": {
                        "width": "",
                        "class": "",
                        "id": ""
                    },
                    "default_value": "",
                    "placeholder": ""
                },
                {
                    "key": "field_5f34e2c0701bb",
                    "label": "LinkedIn",
                    "name": "linkedin",
                    "type": "url",
                    "instructions": "",
                    "required": 0,
                    "conditional_logic": 0,
                    "wrapper": {
                        "width": "",
                        "class": "",
                        "id": ""
                    },
                    "default_value": "",
                    "placeholder": ""
                },
                {
                    "key": "field_5f34e2ca701bc",
                    "label": "YouTube",
                    "name": "youtube",
                    "type": "url",
                    "instructions": "",
                    "required": 0,
                    "conditional_logic": 0,
                    "wrapper": {
                        "width": "",
                        "class": "",
                        "id": ""
                    },
                    "default_value": "",
                    "placeholder": ""
                }
            ]
        },
        {
            "key": "field_5f3faef4c053e",
            "label": "Test",
            "name": "test",
            "type": "text",
            "instructions": "",
            "required": 0,
            "conditional_logic": 0,
            "wrapper": {
                "width": "",
                "class": "",
                "id": ""
            },
            "default_value": "",
            "placeholder": "",
            "prepend": "",
            "append": "",
            "maxlength": ""
        }
    ],
    "location": [
        [
            {
                "param": "options_page",
                "operator": "==",
                "value": "sitewide-content"
            }
        ]
    ],
    "menu_order": 5,
    "position": "normal",
    "style": "default",
    "label_placement": "top",
    "instruction_placement": "label",
    "hide_on_screen": "",
    "active": 1,
    "description": "",
    "modified": 1598009082
}